[{"_id":{"$oid":"6966eae1ff445cab2a818e5b"},"admin_id":null,"admin_name":"시스템 관리자","action":"점주 정보 수정","target_type":"owner","target_id":{"$oid":"6966021474fba250673699c4"},"target_name":"배현이","description":"시스템 관리자님이 배현이에 대해 점주 정보 수정을(를) 수행했습니다.","created_at":{"$date":"2026-01-14T01:01:21.638Z"}},{"_id":{"$oid":"6966eaf9ff445cab2a818e5c"},"admin_id":null,"admin_name":"시스템 관리자","action":"점주 정보 수정","target_type":"owner","target_id":{"$oid":"6966021474fba250673699c4"},"target_name":"배현이","description":"시스템 관리자님이 배현이에 대해 점주 정보 수정을(를) 수행했습니다.","created_at":{"$date":"2026-01-14T01:01:45.629Z"}},{"_id":{"$oid":"6966ee15ff445cab2a818e5d"},"admin_id":null,"admin_name":"시스템 관리자","action":"점주 정보 수정","target_type":"owner","target_id":{"$oid":"6965f27dce26b909edc41e01"},"target_name":"진종혁","description":"시스템 관리자님이 진종혁에 대해 점주 정보 수정을(를) 수행했습니다.","created_at":{"$date":"2026-01-14T01:15:01.492Z"}},{"_id":{"$oid":"6966ef38ff445cab2a818e5e"},"admin_id":null,"admin_name":"시스템 관리자","action":"점주 정보 수정","target_type":"owner","target_id":{"$oid":"6966021474fba250673699c4"},"target_name":"배현이","description":"시스템 관리자님이 배현이에 대해 점주 정보 수정을(를) 수행했습니다.","created_at":{"$date":"2026-01-14T01:19:52.659Z"}},{"_id":{"$oid":"6966ef49ff445cab2a818e5f"},"admin_id":null,"admin_name":"시스템 관리자","action":"점주 정보 수정","target_type":"owner","target_id":{"$oid":"6965f27dce26b909edc41e01"},"target_name":"진종혁","description":"시스템 관리자님이 진종혁에 대해 점주 정보 수정을(를) 수행했습니다.","created_at":{"$date":"2026-01-14T01:20:09.023Z"}},{"_id":{"$oid":"6966f2cbff445cab2a818e60"},"admin_id":null,"admin_name":"시스템 관리자","action":"점주 정보 수정","target_type":"owner","target_id":{"$oid":"6965f27dce26b909edc41e01"},"target_name":"진종혁","description":"시스템 관리자님이 진종혁에 대해 점주 정보 수정을(를) 수행했습니다.","created_at":{"$date":"2026-01-14T01:35:07.548Z"}},{"_id":{"$oid":"6966f342ff445cab2a818e61"},"admin_id":null,"admin_name":"시스템 관리자","action":"점주 정보 수정","target_type":"owner","target_id":{"$oid":"6965f27dce26b909edc41e01"},"target_name":"진종혁","description":"시스템 관리자님이 진종혁에 대해 점주 정보 수정을(를) 수행했습니다.","created_at":{"$date":"2026-01-14T01:37:06.116Z"}},{"_id":{"$oid":"6966f34bff445cab2a818e62"},"admin_id":null,"admin_name":"시스템 관리자","action":"점주 정보 수정","target_type":"owner","target_id":{"$oid":"6965f27dce26b909edc41e01"},"target_name":"진종혁","description":"시스템 관리자님이 진종혁에 대해 점주 정보 수정을(를) 수행했습니다.","created_at":{"$date":"2026-01-14T01:37:15.999Z"}},{"_id":{"$oid":"6966f6d3ff445cab2a818e63"},"admin_id":null,"admin_name":"시스템 관리자","action":"점주 정보 수정","target_type":"owner","target_id":{"$oid":"6965f27dce26b909edc41e01"},"target_name":"진종혁","description":"시스템 관리자님이 진종혁에 대해 점주 정보 수정을(를) 수행했습니다.","created_at":{"$date":"2026-01-14T01:52:19.465Z"}},{"_id":{"$oid":"6966f6ecff445cab2a818e64"},"admin_id":null,"admin_name":"시스템 관리자","action":"점주 정보 수정","target_type":"owner","target_id":{"$oid":"6965f27dce26b909edc41e01"},"target_name":"진종혁","description":"시스템 관리자님이 진종혁에 대해 점주 정보 수정을(를) 수행했습니다.","created_at":{"$date":"2026-01-14T01:52:44.983Z"}},{"_id":{"$oid":"6966f6f2ff445cab2a818e65"},"admin_id":null,"admin_name":"시스템 관리자","action":"점주 정보 수정","target_type":"owner","target_id":{"$oid":"6965f27dce26b909edc41e01"},"target_name":"진종혁","description":"시스템 관리자님이 진종혁에 대해 점주 정보 수정을(를) 수행했습니다.","created_at":{"$date":"2026-01-14T01:52:50.606Z"}},{"_id":{"$oid":"696723085e7bc6cafc7bef37"},"admin_id":null,"admin_name":"시스템 관리자","action":"새 점주 등록","target_type":"owner","target_id":{"$oid":"696723075e7bc6cafc7bef36"},"target_name":"배현이","description":"시스템 관리자님이 배현이에 대해 새 점주 등록을(를) 수행했습니다.","created_at":{"$date":"2026-01-14T05:00:56.052Z"}},{"_id":{"$oid":"69683631439f87fc68614071"},"admin_id":null,"admin_name":"시스템 관리자","action":"새 점주 등록","target_type":"owner","target_id":{"$oid":"69683631439f87fc68614070"},"target_name":"홍길동","description":"시스템 관리자님이 홍길동에 대해 새 점주 등록을(를) 수행했습니다.","created_at":{"$date":"2026-01-15T00:34:57.733Z"}},{"_id":{"$oid":"69683dac23a7a1ba72a37ca8"},"admin_id":null,"admin_name":"시스템 관리자","action":"새 점주 등록","target_type":"owner","target_id":{"$oid":"69683dac23a7a1ba72a37ca7"},"target_name":"차은우","description":"시스템 관리자님이 차은우에 대해 새 점주 등록을(를) 수행했습니다.","created_at":{"$date":"2026-01-15T01:06:52.35Z"}},{"_id":{"$oid":"69683e0b23a7a1ba72a37ca9"},"admin_id":null,"admin_name":"시스템 관리자","action":"점주 정보 수정","target_type":"owner","target_id":{"$oid":"69683dac23a7a1ba72a37ca7"},"target_name":"차은우","description":"시스템 관리자님이 차은우에 대해 점주 정보 수정을(를) 수행했습니다.","created_at":{"$date":"2026-01-15T01:08:27.087Z"}},{"_id":{"$oid":"69683e9023a7a1ba72a37caa"},"admin_id":null,"admin_name":"시스템 관리자","action":"점주 정보 수정","target_type":"owner","target_id":{"$oid":"69683dac23a7a1ba72a37ca7"},"target_name":"차은우","description":"시스템 관리자님이 차은우에 대해 점주 정보 수정을(를) 수행했습니다.","created_at":{"$date":"2026-01-15T01:10:40.876Z"}},{"_id":{"$oid":"696847397b9f34dfc4c9b20f"},"admin_id":null,"admin_name":"시스템 관리자","action":"점주 정보 수정","target_type":"owner","target_id":{"$oid":"69683dac23a7a1ba72a37ca7"},"target_name":"차은우","description":"시스템 관리자님이 차은우에 대해 점주 정보 수정을(를) 수행했습니다.","created_at":{"$date":"2026-01-15T01:47:37.224Z"}},{"_id":{"$oid":"69a673f1ef5d409edabfa802"},"admin_id":null,"admin_name":"시스템 관리자","action":"새 점주 등록","target_type":"owner","target_id":{"$oid":"69a673f1ef5d409edabfa801"},"target_name":"진욱","description":"시스템 관리자님이 진욱에 대해 새 점주 등록을(를) 수행했습니다.","created_at":{"$date":"2026-03-03T05:38:57.688Z"}}]
